MANIFEST.in
README
setup.cfg
setup.py
brabu/__init__.py
brabu/brabu.py
brabu/gui/__init__.py
brabu/gui/__ptd__.py
brabu/gui/brams.py
brabu/gui/bramsrc.py
brabu/ramsin_controller/__init__.py
brabu/ramsin_controller/ramsin_controller.py
brabu/ramsin_controller/ramsin_rule_validator.py
brabu_py2.7.egg-info/PKG-INFO
brabu_py2.7.egg-info/SOURCES.txt
brabu_py2.7.egg-info/dependency_links.txt
brabu_py2.7.egg-info/requires.txt
brabu_py2.7.egg-info/top_level.txt
data/gui/brams.ico
data/gui/bramsIcon.png
data/gui/brams_logo.png
data/gui/estadosl_2007.dbf
data/gui/estadosl_2007.map
data/gui/estadosl_2007.shp
data/gui/estadosl_2007.shx
data/gui/file.ico
data/gui/municip07.dbf
data/gui/municip07.map
data/gui/municip07.shp
data/gui/municip07.shx
data/ramsin_controller/RAMSIN_template
data/ramsin_controller/variables.dat
data/ramsin_controller/patterns/RAMSIN_1km_AMAZON
data/ramsin_controller/patterns/RAMSIN_1km_RIO
data/ramsin_controller/patterns/RAMSIN_SAMERICA
data/ramsin_controller/patterns/RAMSIN_meteo-chem
data/ramsin_controller/patterns/RAMSIN_meteo-only