Metadata-Version: 1.0
Name: brabu-py2.7
Version: 0.1.3
Summary: BRAMS Ramsin Build Utility for Python 2.7
Home-page: http://brams.cptec.inpe.br/
Author: Luiz Flavio Rodrigues, Denis Eiras
Author-email: luflarois@gmail.com, denis.eiras@gmail.com
License: GNU General Public License
Keywords: BRABU BRAMS RAMSIN BUILD UTILITY
Platform: UNKNOWN
